forstate.py
forstate-0.0.2.dist-info/LICENSE
forstate-0.0.2.dist-info/WHEEL
forstate-0.0.2.dist-info/METADATA
forstate-0.0.2.dist-info/RECORD
