Metadata-Version: 2.1
Name: forstate
Version: 0.0.2
Summary: Dispatch methods according to a state value
Author-email: Salvador Fandiño <sfandino@yahoo.com>
Classifier: License :: OSI Approved :: MIT License
Project-URL: Home, http://github.com/salva/py-forstate
